.gitignore
MANIFEST.in
setup.cfg
setup.py
conf/__init__.py
conf/chat.cfg
conf/demo.cfg
conf/gallery.cfg
conf/gallery1.cfg
conf/gallery10.cfg
conf/gallery2.cfg
conf/gallery3.cfg
conf/gallery4.cfg
conf/gallery5.cfg
conf/gallery6.cfg
conf/gallery7.cfg
conf/gallery8.cfg
conf/gallery9.cfg
conf/gallery_tutorial.cfg
conf/jewels.cfg
conf/portal.cfg
conf/wiki.cfg
conf/wiki1.cfg
conf/wiki10.cfg
conf/wiki11.cfg
conf/wiki12.cfg
conf/wiki13.cfg
conf/wiki14.cfg
conf/wiki15.cfg
conf/wiki16.cfg
conf/wiki17.cfg
conf/wiki18.cfg
conf/wiki2.cfg
conf/wiki3.cfg
conf/wiki4.cfg
conf/wiki5.cfg
conf/wiki6.cfg
conf/wiki7.cfg
conf/wiki8.cfg
conf/wiki9.cfg
conf/wiki_tutorial.cfg
data/__init__.py
docs/CHANGELOG.rst
docs/LICENSE.txt
nagare/__init__.py
nagare.examples.egg-info/PKG-INFO
nagare.examples.egg-info/SOURCES.txt
nagare.examples.egg-info/dependency_links.txt
nagare.examples.egg-info/entry_points.txt
nagare.examples.egg-info/namespace_packages.txt
nagare.examples.egg-info/not-zip-safe
nagare.examples.egg-info/requires.txt
nagare.examples.egg-info/top_level.txt
nagare/examples/__init__.py
nagare/examples/calculator.py
nagare/examples/chat.py
nagare/examples/color.py
nagare/examples/counter.py
nagare/examples/demo.py
nagare/examples/form.py
nagare/examples/img.py
nagare/examples/jewels.py
nagare/examples/number.py
nagare/examples/tictactoe.py
nagare/examples/widgets.py
nagare/examples/gallery/__init__.py
nagare/examples/gallery/dragon.jpg
nagare/examples/gallery/gallery.py
nagare/examples/gallery/gallery1.py
nagare/examples/gallery/gallery10.py
nagare/examples/gallery/gallery2.py
nagare/examples/gallery/gallery3.py
nagare/examples/gallery/gallery4.py
nagare/examples/gallery/gallery5.py
nagare/examples/gallery/gallery6.py
nagare/examples/gallery/gallery7.py
nagare/examples/gallery/gallery8.py
nagare/examples/gallery/gallery9.py
nagare/examples/gallery/gallerydata.py
nagare/examples/gallery/gallerydata2.py
nagare/examples/gallery/gallerydeclarative.py
nagare/examples/gallery/gallerysqlalchemy.py
nagare/examples/gallery/thumb.py
nagare/examples/portal/__init__.py
nagare/examples/portal/calculator.py
nagare/examples/portal/counter.py
nagare/examples/portal/html.py
nagare/examples/portal/portal.py
nagare/examples/portal/source_viewer.py
nagare/examples/portal/tictactoe.py
nagare/examples/wiki/__init__.py
